tests/__init__.py
tests/conftest.py
tests/functional/__init__.py
tests/functional/test_dependant_install.py
tests/functional/test_run_python_file.py
tests/functional/test_source_execution.py
tests/functional/test_source_package.py
tests/integration/__init__.py
tests/integration/test_cffi.py
tests/integration/test_console_scripts.py
tests/integration/test_dependant_install.py
tests/integration/test_docopt.py
tests/integration/test_libvirt.py
tests/integration/test_list.py
tests/integration/test_ncclient.py
tests/integration/test_no_binary_no_deps.py
tests/integration/test_package_name_canonicalization.py
tests/integration/test_source_execution.py
tests/integration/test_typed_ast.py
tests/integration/test_upgrade_and_version_reported.py
tests/integration/typed_ast/__init__.py
tests/projects/dependant/pyproject.toml
tests/projects/dependant/tpmpd/__init__.py
tests/projects/main/pyproject.toml
tests/projects/main/tpmp/__init__.py
tests/support/__init__.py
tests/support/helpers.py
tests/support/projects/dependant/pyproject.toml
tests/support/projects/dependant/tpmpd/__init__.py
tests/support/projects/main/pyproject.toml
tests/support/projects/main/tpmp/__init__.py
tests/unit/__init__.py
tests/unit/test_cli.py
tiamatpip/__init__.py
tiamatpip/cli.py
tiamatpip/configure.py
tiamatpip/earlypatches.py
tiamatpip/patches.py
tiamatpip/pip_patches.py
tiamatpip/py.typed
tiamatpip/store.py
tiamatpip/utils.py
tiamatpip/version.py
tiamatpip/ext/__init__.py
tiamatpip/ext/pip/LICENSE.txt
tiamatpip/ext/pip/__init__.py
tiamatpip/ext/pip/__main__.py
tiamatpip/ext/pip/__pip-runner__.py
tiamatpip/ext/pip/py.typed
tiamatpip/ext/pip/_internal/__init__.py
tiamatpip/ext/pip/_internal/build_env.py
tiamatpip/ext/pip/_internal/cache.py
tiamatpip/ext/pip/_internal/configuration.py
tiamatpip/ext/pip/_internal/exceptions.py
tiamatpip/ext/pip/_internal/main.py
tiamatpip/ext/pip/_internal/pyproject.py
tiamatpip/ext/pip/_internal/self_outdated_check.py
tiamatpip/ext/pip/_internal/wheel_builder.py
tiamat_pip-1.11.0.dist-info/LICENSE
tiamat_pip-1.11.0.dist-info/METADATA
tiamat_pip-1.11.0.dist-info/WHEEL
tiamat_pip-1.11.0.dist-info/entry_points.txt
tiamat_pip-1.11.0.dist-info/top_level.txt
tiamat_pip-1.11.0.dist-info/RECORD
