Metadata-Version: 2.1
Name: tiamat-pip
Version: 1.11.0
Summary: Pip handling for tiamat projects
Home-page: http://saltstack.com
Author: Pedro Algarvio
Author-email: pedro@algarvio.me
License: Apache Software License 2.0
Project-URL: Source, https://gitlab.com/saltstack/pop/tiamat-pip
Project-URL: Tracker, https://gitlab.com/saltstack/pop/tiamat-pip/-/issues
Platform: unix
Platform: linux
Platform: osx
Platform: cygwin
Platform: win32
Classifier: Programming Language :: Python
Classifier: Programming Language :: Cython
Classifier: Programming Language :: Python :: 3
Classifier: Programming Language :: Python :: 3 :: Only
Classifier: Programming Language :: Python :: 3.6
Classifier: Programming Language :: Python :: 3.7
Classifier: Programming Language :: Python :: 3.8
Classifier: Programming Language :: Python :: 3.9
Classifier: Development Status :: 4 - Beta
Classifier: Intended Audience :: Developers
Classifier: License :: OSI Approved :: Apache Software License
Requires-Python: >=3.7
License-File: LICENSE
Requires-Dist: pip (<22.3,>=22.2)
Requires-Dist: PyInstaller (>=4.0)
Requires-Dist: importlib-metadata
Requires-Dist: typing-extensions ; python_version < "3.8"
